[
  {
    "f_name": "Nina",
    "l_name": "Heidenreich",
    "username": "Reggie89",
    "password_digest": "password"
  },
  {
    "f_name": "Veronica",
    "l_name": "Rutherford",
    "username": "Otilia_Little",
    "password_digest": "password"
  },
  {
    "f_name": "Elroy",
    "l_name": "Denesik",
    "username": "Camron_Wisoky33",
    "password_digest": "password"
  },
  {
    "f_name": "Aimee",
    "l_name": "Waelchi",
    "username": "Drake89",
    "password_digest": "password"
  },
  {
    "f_name": "Telly",
    "l_name": "Shields",
    "username": "Dylan73",
    "password_digest": "password"
  },
  {
    "f_name": "Mallory",
    "l_name": "Keeling",
    "username": "Elliot38",
    "password_digest": "password"
  },
  {
    "f_name": "Hassan",
    "l_name": "Kutch",
    "username": "Lambert37",
    "password_digest": "password"
  },
  {
    "f_name": "Kale",
    "l_name": "Schaden",
    "username": "Alvis.Gislason95",
    "password_digest": "password"
  },
  {
    "f_name": "Kennedi",
    "l_name": "Ondricka",
    "username": "Mable57",
    "password_digest": "password"
  },
  {
    "f_name": "Makenna",
    "l_name": "Jacobson",
    "username": "Leola.Lowe",
    "password_digest": "password"
  }
]